{
  "kind": "singleType",
  "collectionName": "react_native_developments",
  "info": {
    "singularName": "react-native-development",
    "pluralName": "react-native-developments",
    "displayName": "React Native Development"
  },
  "options": {
    "draftAndPublish": true
  },
  "pluginOptions": {},
  "attributes": {
    "Title": {
      "type": "richtext"
    },
    "Descipation": {
      "type": "richtext"
    },
    "Image": {
      "allowedTypes": [
        "images",
        "files",
        "videos",
        "audios"
      ],
      "type": "media",
      "multiple": false
    },
    "SubTitle": {
      "type": "richtext"
    },
    "SubDescipation": {
      "type": "richtext"
    },
    "Image1": {
      "allowedTypes": [
        "images",
        "files",
        "videos",
        "audios"
      ],
      "type": "media",
      "multiple": false
    }
  }
}
