{
  "kind": "collectionType",
  "collectionName": "game_ui_and_ux_development_processes",
  "info": {
    "singularName": "game-ui-and-ux-development-process",
    "pluralName": "game-ui-and-ux-development-processes",
    "displayName": "Game UI & UX Development Process"
  },
  "options": {
    "draftAndPublish": true
  },
  "pluginOptions": {},
  "attributes": {
    "Title": {
      "type": "richtext"
    },
    "Description": {
      "type": "richtext"
    },
    "Image": {
      "allowedTypes": [
        "images",
        "files",
        "videos",
        "audios"
      ],
      "type": "media",
      "multiple": false
    }
  }
}
